setup.py
aws_acm_cert_validator/__init__.py
aws_acm_cert_validator/logic.py
aws_acm_cert_validator/main.py
aws_acm_cert_validator.egg-info/PKG-INFO
aws_acm_cert_validator.egg-info/SOURCES.txt
aws_acm_cert_validator.egg-info/dependency_links.txt
aws_acm_cert_validator.egg-info/entry_points.txt
aws_acm_cert_validator.egg-info/requires.txt
aws_acm_cert_validator.egg-info/top_level.txt
aws_acm_cert_validator_cli/__init__.py
aws_acm_cert_validator_cli/__main__.py
aws_acm_cert_validator_lambda/cr_response.py
aws_acm_cert_validator_lambda/handler.py
aws_acm_cert_validator_lambda/handler_batch.py