Metadata-Version: 1.2
Name: aws-acm-cert-validator
Version: 0.2.1
Summary: AWS Acm Certificate issuance and validation
Home-page: http://github.com/base2Services/cloudformation-custom-resources
Author: Base2Services R&D
Author-email: itsupport@base2services.com
License: UNKNOWN
Keywords: aws acm ssl certificate
Platform: UNKNOWN
Classifier: Development Status :: 3 - Alpha
Classifier: Programming Language :: Python :: 3.6
Classifier: Intended Audience :: System Administrators
Classifier: Intended Audience :: Information Technology
Classifier: License :: OSI Approved :: MIT License
Requires-Python: >=3.6
